{
  "type": "forge:conditional",
  "recipes": [
    {
      "conditions": [
        {
          "type": "forge:and",
          "values": [
            {
              "type": "forge:mod_loaded",
              "modid": "endergetic"
            },
            {
              "type": "forge:mod_loaded",
              "modid": "woodworks"
            }
          ]
        }
      ],
      "recipe": {
        "type": "minecraft:crafting_shaped",
        "key": {
          "f": {
            "item": "exnihilosequentia:beehive_frame"
          },
          "x": {
            "item": "endergetic:poise_planks"
          }
        },
        "pattern": [
          "xxx",
          "fff",
          "xxx"
        ],
        "result": {
          "item": "endergetic:poise_beehive"
        }
      }
    }
  ]
}